setup.py
src/figgler/__init__.py
src/figgler/core.py
src/figgler.egg-info/PKG-INFO
src/figgler.egg-info/SOURCES.txt
src/figgler.egg-info/dependency_links.txt
src/figgler.egg-info/requires.txt
src/figgler.egg-info/top_level.txt