Metadata-Version: 1.0
Name: figgler
Version: 1.1.1
Summary: Utilities for reading environment variables in containers instrumented with fig.
Home-page: https://github.com/karolmajta/figgler-python
Author: Karol Majta
Author-email: karolmajta@gmail.com
License: MIT
Platform: UNKNOWN
